flatgeobuf_pyrust-0.2.2.dist-info/METADATA
flatgeobuf_pyrust-0.2.2.dist-info/WHEEL
flatgeobuf_pyrust/__init__.py
flatgeobuf_pyrust/flatgeobuf_pyrust.cpython-310-x86_64-linux-gnu.so
flatgeobuf_pyrust-0.2.2.dist-info/RECORD
