Metadata-Version: 2.1
Name: flatgeobuf-pyrust
Version: 0.2.2
Classifier: Intended Audience :: Developers
Classifier: Programming Language :: Python :: 3
Classifier: Topic :: Scientific/Engineering :: GIS
Summary: Encoding and decoding to and from Flatgeobuf and WKB.
Keywords: flatgeobuf,ogc,features
Author-email: Adrien Glauser <mrnycticorax@gmail.com>
Project-URL: homepage, https://github.com/opengisch
Project-URL: repository, https://github.com/opengisch
